odoo9_addon_website_crm_quick_answer-9.0.1.0.0-py2.7-nspkg.pth
odoo9_addon_website_crm_quick_answer-9.0.1.0.0.dist-info/DESCRIPTION.rst
odoo9_addon_website_crm_quick_answer-9.0.1.0.0.dist-info/METADATA
odoo9_addon_website_crm_quick_answer-9.0.1.0.0.dist-info/RECORD
odoo9_addon_website_crm_quick_answer-9.0.1.0.0.dist-info/WHEEL
odoo9_addon_website_crm_quick_answer-9.0.1.0.0.dist-info/metadata.json
odoo9_addon_website_crm_quick_answer-9.0.1.0.0.dist-info/namespace_packages.txt
odoo9_addon_website_crm_quick_answer-9.0.1.0.0.dist-info/top_level.txt
odoo_addons/website_crm_quick_answer/README.rst
odoo_addons/website_crm_quick_answer/__init__.py
odoo_addons/website_crm_quick_answer/__openerp__.py
odoo_addons/website_crm_quick_answer/data/automation.xml
odoo_addons/website_crm_quick_answer/i18n/ca.po
odoo_addons/website_crm_quick_answer/i18n/de.po
odoo_addons/website_crm_quick_answer/i18n/el_GR.po
odoo_addons/website_crm_quick_answer/i18n/es.po
odoo_addons/website_crm_quick_answer/i18n/fr.po
odoo_addons/website_crm_quick_answer/i18n/it.po
odoo_addons/website_crm_quick_answer/i18n/pt_BR.po
odoo_addons/website_crm_quick_answer/i18n/sl.po
odoo_addons/website_crm_quick_answer/migrations/9.0.1.0.0/pre-migrate.py
odoo_addons/website_crm_quick_answer/models/__init__.py
odoo_addons/website_crm_quick_answer/models/crm_lead.py
odoo_addons/website_crm_quick_answer/static/description/icon.png
